eg4_mcp_server/__init__.py
eg4_mcp_server/__main__.py
eg4_mcp_server/py.typed
eg4_mcp_server/server.py
eg4_mcp_server-0.1.5.dist-info/METADATA
eg4_mcp_server-0.1.5.dist-info/WHEEL
eg4_mcp_server-0.1.5.dist-info/entry_points.txt
eg4_mcp_server-0.1.5.dist-info/licenses/LICENSE.md
eg4_mcp_server-0.1.5.dist-info/RECORD
