Metadata-Version: 2.4
Name: eg4-mcp-server
Version: 0.1.5
Summary: Model Context Protocol server for EG4 solar inverter monitoring and control
Project-URL: Homepage, https://github.com/matt-dreyer/EG4_MCP_server
Project-URL: Repository, https://github.com/matt-dreyer/EG4_MCP_server
Project-URL: Documentation, https://github.com/matt-dreyer/EG4_MCP_server#readme
Project-URL: Issues, https://github.com/matt-dreyer/EG4_MCP_server/issues
Project-URL: Discussions, https://github.com/matt-dreyer/EG4_MCP_server/discussions
Project-URL: Changelog, https://github.com/matt-dreyer/EG4_MCP_server/blob/main/CHANGELOG.md
Author-email: Matt Dreyer <matt_dreyer@hotmail.com>
Maintainer-email: Matt Dreyer <matt_dreyer@hotmail.com>
License: MIT License
License-File: LICENSE.md
Keywords: battery,eg4,energy,home-automation,inverter,mcp,monitoring,photovoltaic,renewable,solar
Classifier: Development Status :: 4 - Beta
Classifier: Environment :: Console
Classifier: Intended Audience :: Developers
Classifier: Intended Audience :: End Users/Desktop
Classifier: License :: OSI Approved :: MIT License
Classifier: Natural Language :: English
Classifier: Operating System :: OS Independent
Classifier: Programming Language :: Python :: 3
Classifier: Programming Language :: Python :: 3.10
Classifier: Programming Language :: Python :: 3.11
Classifier: Programming Language :: Python :: 3.12
Classifier: Topic :: Home Automation
Classifier: Topic :: Scientific/Engineering
Classifier: Topic :: System :: Monitoring
Classifier: Topic :: Utilities
Requires-Python: >=3.10
Requires-Dist: aiohttp>=3.8.5
Requires-Dist: eg4-python
Requires-Dist: httpx>=0.28.1
Requires-Dist: mcp[cli]>=1.11.0
Requires-Dist: python-dotenv>=1.0.0
Provides-Extra: dev
Requires-Dist: black>=23.0.0; extra == 'dev'
Requires-Dist: mypy>=1.5.0; extra == 'dev'
Requires-Dist: pre-commit>=3.0.0; extra == 'dev'
Requires-Dist: pytest-asyncio>=1.0.0; extra == 'dev'
Requires-Dist: pytest>=8.4.0; extra == 'dev'
Requires-Dist: ruff>=0.1.0; extra == 'dev'
Provides-Extra: docs
Requires-Dist: myst-parser>=2.0.0; extra == 'docs'
Requires-Dist: sphinx-rtd-theme>=1.3.0; extra == 'docs'
Requires-Dist: sphinx>=6.0.0; extra == 'docs'
Provides-Extra: test
Requires-Dist: pytest-asyncio>=1.0.0; extra == 'test'
Requires-Dist: pytest-cov>=4.0.0; extra == 'test'
Requires-Dist: pytest-mock>=3.10.0; extra == 'test'
Requires-Dist: pytest>=8.4.0; extra == 'test'
